multidim/__init__.py
multidim/enr.py
multidim/enr2.py
multidim/nball.py
multidim/ncube.py
multidim/nsimplex.py
multidim/nsphere.py
multidim-0.1.6.dist-info/LICENSE
multidim-0.1.6.dist-info/METADATA
multidim-0.1.6.dist-info/WHEEL
multidim-0.1.6.dist-info/top_level.txt
multidim-0.1.6.dist-info/RECORD
